diffqcp/__init__.py
diffqcp/_helpers.py
diffqcp/linops.py
diffqcp/problem_data.py
diffqcp/qcp.py
diffqcp/qcp_derivs.py
diffqcp/cones/__init__.py
diffqcp/cones/abstract_projector.py
diffqcp/cones/canonical.py
diffqcp/cones/exp.py
diffqcp/cones/pow.py
diffqcp-0.4.4.dist-info/licenses/LICENSE.md
diffqcp-0.4.4.dist-info/METADATA
diffqcp-0.4.4.dist-info/WHEEL
diffqcp-0.4.4.dist-info/top_level.txt
diffqcp-0.4.4.dist-info/RECORD
