Metadata-Version: 2.4
Name: diffqcp
Version: 0.4.4
Summary: Engine to compute Jacobian-vector and vector-Jacobian products for (convex) quadratic cone programs.
Requires-Python: >=3.11
License-File: LICENSE.md
Requires-Dist: equinox>=0.12.2
Requires-Dist: jax>=0.7.2
Requires-Dist: jaxtyping>=0.3.2
Requires-Dist: lineax
Requires-Dist: numpy>=2.3.1
Requires-Dist: scipy>=1.15.3
Provides-Extra: gpu
Requires-Dist: cupy-cuda12x>=13.6.0; extra == "gpu"
Requires-Dist: jax[cuda12]>=0.7.2; extra == "gpu"
Requires-Dist: nvmath-python[cu12]>=0.7.0; extra == "gpu"
Dynamic: license-file
